{
  "usuarios": [
    {
      "id": "272891",
      "username": "juanjeadmin",
      "password": "juanje"
    },
    {
      "id": "602544",
      "username": "vegapunk",
      "password": "punk"
    },
    {
      "id": "287736",
      "username": "Blasco",
      "password": "ralts"
    },
    {
      "id": "509534",
      "username": "Red",
      "password": "pika"
    },
    {
      "id": "494082",
      "username": "Juanjesito",
      "password": "juanje"
    },
    {
      "id": 904711,
      "username": "nando",
      "password": "nando"
    },
    {
      "id": 51928,
      "username": "Juanjenit",
      "password": "juanje"
    },
    {
      "id": 974304,
      "username": "Mariorob",
      "password": "mario"
    },
    {
      "id": 436823,
      "username": "werwer",
      "password": "werwer"
    },
    {
      "id": 581520,
      "username": "asdasd",
      "password": "asdasd"
    },
    {
      "id": 404890,
      "username": "Blasco2",
      "password": "blascop"
    }
  ]
}